{
  "gitSyncId": "6a0f4543dbfe62522fc87116_4fb12db2-77f5-4045-8ecf-27f1d648e481",
  "id": "Team_members_getTeamMembers",
  "pluginId": "postgres-plugin",
  "pluginType": "DB",
  "unpublishedAction": {
    "actionConfiguration": {
      "body": "SELECT f_name, l_name FROM person p\njoin department_team_member dtm on dtm.person_id = p.person_id\njoin department_team dt on dt.team_id = dtm.team_id\nwhere dt.name_en = {{appsmith.store.selectedTeam}}\norder by p.l_name",
      "encodeParamsToggle": true,
      "paginationType": "NONE",
      "pluginSpecifiedTemplates": [
        {
          "value": true
        }
      ],
      "timeoutInMillisecond": 10000
    },
    "confirmBeforeExecute": false,
    "datasource": {
      "id": "CHUM_dev",
      "isAutoGenerated": false,
      "name": "CHUM_dev",
      "pluginId": "postgres-plugin"
    },
    "dynamicBindingPathList": [
      {
        "key": "body"
      }
    ],
    "name": "getTeamMembers",
    "pageId": "Team_members",
    "runBehaviour": "AUTOMATIC",
    "userSetOnLoad": false
  }
}